pypetrophysics/__init__.py
pypetrophysics/clayshale.py
pypetrophysics/convert.py
pypetrophysics/miscfuncs.py
pypetrophysics/porosity.py
pypetrophysics/salinity.py
pypetrophysics/saturation.py
pypetrophysics/temperature.py
pypetrophysics-0.2.0.dist-info/DESCRIPTION.rst
pypetrophysics-0.2.0.dist-info/METADATA
pypetrophysics-0.2.0.dist-info/RECORD
pypetrophysics-0.2.0.dist-info/WHEEL
pypetrophysics-0.2.0.dist-info/metadata.json
pypetrophysics-0.2.0.dist-info/top_level.txt
