Metadata-Version: 2.0
Name: pypetrophysics
Version: 0.2.0
Summary: A library of petrophysical calculations
Home-page: https://github.com/andymcdgeo/PyPetrophysics
Author: Andy McDonald
Author-email: UNKNOWN
License: UNKNOWN
Platform: UNKNOWN
